picoagents/__init__.py
picoagents/_cancellation_token.py
picoagents/_component_config.py
picoagents/_middleware.py
picoagents/_otel.py
picoagents/context.py
picoagents/messages.py
picoagents/types.py
picoagents/agents/__init__.py
picoagents/agents/_agent.py
picoagents/agents/_agent_as_tool.py
picoagents/agents/_base.py
picoagents/agents/_computer_use/__init__.py
picoagents/agents/_computer_use/_computer_use.py
picoagents/agents/_computer_use/_interface_clients.py
picoagents/agents/_computer_use/_planning_models.py
picoagents/agents/_computer_use/_playwright_tools.py
picoagents/cli/__init__.py
picoagents/cli/_main.py
picoagents/eval/__init__.py
picoagents/eval/_base.py
picoagents/eval/_runner.py
picoagents/eval/_targets.py
picoagents/eval/examples/__init__.py
picoagents/eval/examples/basic_evaluation.py
picoagents/eval/judges/__init__.py
picoagents/eval/judges/_base.py
picoagents/eval/judges/_composite.py
picoagents/eval/judges/_llm.py
picoagents/eval/judges/_reference.py
picoagents/llm/__init__.py
picoagents/llm/_anthropic.py
picoagents/llm/_azure_openai.py
picoagents/llm/_base.py
picoagents/llm/_openai.py
picoagents/memory/__init__.py
picoagents/memory/_base.py
picoagents/memory/_chromadb.py
picoagents/orchestration/__init__.py
picoagents/orchestration/_ai.py
picoagents/orchestration/_base.py
picoagents/orchestration/_handoff.py
picoagents/orchestration/_plan.py
picoagents/orchestration/_round_robin.py
picoagents/termination/__init__.py
picoagents/termination/_base.py
picoagents/termination/_cancellation.py
picoagents/termination/_composite.py
picoagents/termination/_external.py
picoagents/termination/_function_call.py
picoagents/termination/_handoff.py
picoagents/termination/_max_message.py
picoagents/termination/_text_mention.py
picoagents/termination/_timeout.py
picoagents/termination/_token_usage.py
picoagents/tools/__init__.py
picoagents/tools/_base.py
picoagents/tools/_coding_tools.py
picoagents/tools/_core_tools.py
picoagents/tools/_decorator.py
picoagents-0.3.2.dist-info/METADATA
picoagents-0.3.2.dist-info/WHEEL
picoagents-0.3.2.dist-info/entry_points.txt
picoagents-0.3.2.dist-info/licenses/LICENSE
picoagents-0.3.2.dist-info/RECORD
