Metadata-Version: 2.4
Name: picoagents
Version: 0.3.2
Summary: A minimal multi-agent framework for educational purposes
Project-URL: Homepage, https://github.com/victordibia/designing-multiagent-systems
Project-URL: Documentation, https://github.com/victordibia/designing-multiagent-systems#readme
Project-URL: Repository, https://github.com/victordibia/designing-multiagent-systems
Author-email: Victor Dibia <victordibia@gmail.com>
License-Expression: MIT
License-File: LICENSE
Keywords: agents,ai,educational,llm,multi-agent
Classifier: Development Status :: 3 - Alpha
Classifier: Intended Audience :: Developers
Classifier: Intended Audience :: Education
Classifier: License :: OSI Approved :: MIT License
Classifier: Programming Language :: Python :: 3
Classifier: Programming Language :: Python :: 3.10
Classifier: Programming Language :: Python :: 3.11
Classifier: Programming Language :: Python :: 3.12
Classifier: Topic :: Scientific/Engineering :: Artificial Intelligence
Classifier: Topic :: Software Development :: Libraries :: Python Modules
Requires-Python: >=3.10
Requires-Dist: openai==1.107.1
Requires-Dist: pydantic>=2.0.0
Requires-Dist: requests>=2.25.0
Requires-Dist: typing-extensions>=4.0.0
Provides-Extra: all
Requires-Dist: anthropic>=0.70.0; extra == 'all'
Requires-Dist: arxiv>=2.0.0; extra == 'all'
Requires-Dist: beautifulsoup4>=4.12.0; extra == 'all'
Requires-Dist: chromadb>=0.4.0; extra == 'all'
Requires-Dist: fastapi>=0.100.0; extra == 'all'
Requires-Dist: html2text>=2020.1.16; extra == 'all'
Requires-Dist: httpx>=0.24.0; extra == 'all'
Requires-Dist: matplotlib; extra == 'all'
Requires-Dist: mcp>=1.0.0; extra == 'all'
Requires-Dist: pillow>=10.0.0; extra == 'all'
Requires-Dist: playwright>=1.40.0; extra == 'all'
Requires-Dist: python-dotenv; extra == 'all'
Requires-Dist: python-multipart>=0.0.6; extra == 'all'
Requires-Dist: sentence-transformers>=2.2.0; extra == 'all'
Requires-Dist: uvicorn[standard]>=0.23.0; extra == 'all'
Requires-Dist: yfinance; extra == 'all'
Requires-Dist: youtube-transcript-api>=0.6.0; extra == 'all'
Provides-Extra: anthropic
Requires-Dist: anthropic>=0.70.0; extra == 'anthropic'
Provides-Extra: computer-use
Requires-Dist: beautifulsoup4>=4.12.0; extra == 'computer-use'
Requires-Dist: pillow>=10.0.0; extra == 'computer-use'
Requires-Dist: playwright>=1.40.0; extra == 'computer-use'
Provides-Extra: dev
Requires-Dist: black; extra == 'dev'
Requires-Dist: flake8; extra == 'dev'
Requires-Dist: isort; extra == 'dev'
Requires-Dist: mypy; extra == 'dev'
Requires-Dist: poethepoet; extra == 'dev'
Requires-Dist: pyright; extra == 'dev'
Requires-Dist: pytest-asyncio>=0.21.0; extra == 'dev'
Requires-Dist: pytest-cov; extra == 'dev'
Requires-Dist: pytest>=7.0.0; extra == 'dev'
Provides-Extra: examples
Requires-Dist: matplotlib; extra == 'examples'
Requires-Dist: python-dotenv; extra == 'examples'
Requires-Dist: yfinance; extra == 'examples'
Provides-Extra: frameworks
Requires-Dist: agent-framework[azure]>=0.1.0; extra == 'frameworks'
Requires-Dist: claude-agent-sdk>=0.1.0; extra == 'frameworks'
Requires-Dist: google-adk>=0.1.0; extra == 'frameworks'
Requires-Dist: langchain-openai>=1.1.0; extra == 'frameworks'
Requires-Dist: langchain>=1.1.0; extra == 'frameworks'
Requires-Dist: langgraph>=1.0.0; extra == 'frameworks'
Requires-Dist: python-dotenv; extra == 'frameworks'
Provides-Extra: mcp
Requires-Dist: mcp>=1.0.0; extra == 'mcp'
Provides-Extra: otel
Requires-Dist: opentelemetry-api~=1.38.0; extra == 'otel'
Requires-Dist: opentelemetry-exporter-otlp-proto-http~=1.38.0; extra == 'otel'
Requires-Dist: opentelemetry-sdk~=1.38.0; extra == 'otel'
Provides-Extra: rag
Requires-Dist: chromadb>=0.4.0; extra == 'rag'
Requires-Dist: sentence-transformers>=2.2.0; extra == 'rag'
Provides-Extra: research
Requires-Dist: arxiv>=2.0.0; extra == 'research'
Requires-Dist: beautifulsoup4>=4.12.0; extra == 'research'
Requires-Dist: html2text>=2020.1.16; extra == 'research'
Requires-Dist: httpx>=0.24.0; extra == 'research'
Requires-Dist: youtube-transcript-api>=0.6.0; extra == 'research'
Provides-Extra: web
Requires-Dist: fastapi>=0.100.0; extra == 'web'
Requires-Dist: python-multipart>=0.0.6; extra == 'web'
Requires-Dist: uvicorn[standard]>=0.23.0; extra == 'web'
